{
  "countries": [
    {
      "id": "uk",
      "name": "United Kingdom",
      "cities": [
        {
          "name": "London",
          "petType": [
            {
              "name": "General",
              "careType": [
                {
                  "name": "pet sitting",
                  "price": 52
                }
              ]
            },
            {
              "name": "Dog",
              "careType": [
                {
                  "name": "dog sitting",
                  "price": 58.5
                },
                {
                  "name": "dog walking",
                  "price": 17.49
                },
                {
                  "name": "dog kennels",
                  "price": 78
                },
                {
                  "name": "doggy daycare",
                  "price": 71.5
                },
                {
                  "name": "dog drop-in visits",
                  "price": 14.3
                }
              ]
            },
            {
              "name": "Cat",
              "careType": [
                {
                  "name": "cat sitting",
                  "price": 45.5
                },
                {
                  "name": "cat drop-in visits",
                  "price": 14.3
                },
                {
                  "name": "catteries",
                  "price": 19.5
                }
              ]
            }
          ]
        },
        {
          "name": "Edinburgh",
          "petType": [
            {
              "name": "General",
              "careType": [
                {
                  "name": "pet sitting",
                  "price": 46.15
                }
              ]
            },
            {
              "name": "Dog",
              "careType": [
                {
                  "name": "dog sitting",
                  "price": 68.25
                },
                {
                  "name": "dog walking",
                  "price": 14.3
                },
                {
                  "name": "dog kennels",
                  "price": 24.51
                },
                {
                  "name": "doggy daycare",
                  "price": 31.2
                },
                {
                  "name": "dog drop-in visits",
                  "price": 18.2
                }
              ]
            },
            {
              "name": "Cat",
              "careType": [
                {
                  "name": "cat sitting",
                  "price": 58.5
                },
                {
                  "name": "cat drop-in visits",
                  "price": 19.5
                },
                {
                  "name": "catteries",
                  "price": 24.51
                }
              ]
            }
          ]
        },
        {
          "name": "Manchester",
          "petType": [
            {
              "name": "General",
              "careType": [
                {
                  "name": "pet sitting",
                  "price": 60.45
                }
              ]
            },
            {
              "name": "Dog",
              "careType": [
                {
                  "name": "dog sitting",
                  "price": 60.45
                },
                {
                  "name": "dog walking",
                  "price": 16.9
                },
                {
                  "name": "dog kennels",
                  "price": 39.46
                },
                {
                  "name": "doggy daycare",
                  "price": 39
                },
                {
                  "name": "dog drop-in visits",
                  "price": 26
                }
              ]
            },
            {
              "name": "Cat",
              "careType": [
                {
                  "name": "cat sitting",
                  "price": 60.45
                },
                {
                  "name": "cat drop-in visits",
                  "price": 13
                },
                {
                  "name": "catteries",
                  "price": 13
                }
              ]
            }
          ]
        },
        {
          "name": "Brighton",
          "petType": [
            {
              "name": "General",
              "careType": [
                {
                  "name": "pet sitting",
                  "price": 48.75
                }
              ]
            },
            {
              "name": "Dog",
              "careType": [
                {
                  "name": "dog sitting",
                  "price": 54.6
                },
                {
                  "name": "dog walking",
                  "price": 18.85
                },
                {
                  "name": "dog kennels",
                  "price": 36.4
                },
                {
                  "name": "doggy daycare",
                  "price": 54.6
                },
                {
                  "name": "dog drop-in visits",
                  "price": 25.35
                }
              ]
            },
            {
              "name": "Cat",
              "careType": [
                {
                  "name": "cat sitting",
                  "price": 54.6
                },
                {
                  "name": "cat drop-in visits",
                  "price": 25.35
                },
                {
                  "name": "catteries",
                  "price": 23.4
                }
              ]
            }
          ]
        },
        {
          "name": "Oxford",
          "petType": [
            {
              "name": "General",
              "careType": [
                {
                  "name": "pet sitting",
                  "price": 58.5
                }
              ]
            },
            {
              "name": "Dog",
              "careType": [
                {
                  "name": "dog sitting",
                  "price": 58.5
                },
                {
                  "name": "dog walking",
                  "price": 19.5
                },
                {
                  "name": "dog kennels",
                  "price": 101.4
                },
                {
                  "name": "doggy daycare",
                  "price": 65
                },
                {
                  "name": "dog drop-in visits",
                  "price": 26
                }
              ]
            },
            {
              "name": "Cat",
              "careType": [
                {
                  "name": "cat sitting",
                  "price": 58.5
                },
                {
                  "name": "cat drop-in visits",
                  "price": 26
                },
                {
                  "name": "catteries",
                  "price": 18.2
                }
              ]
            }
          ]
        },
        {
          "name": "Glasgow",
          "petType": [
            {
              "name": "General",
              "careType": [
                {
                  "name": "pet sitting",
                  "price": 59.15
                }
              ]
            },
            {
              "name": "Dog",
              "careType": [
                {
                  "name": "dog sitting",
                  "price": 59.15
                },
                {
                  "name": "dog walking",
                  "price": 13
                },
                {
                  "name": "dog kennels",
                  "price": 31.53
                },
                {
                  "name": "doggy daycare",
                  "price": 45.5
                },
                {
                  "name": "dog drop-in visits",
                  "price": 23.4
                }
              ]
            },
            {
              "name": "Cat",
              "careType": [
                {
                  "name": "cat sitting",
                  "price": 59.15
                },
                {
                  "name": "cat drop-in visits",
                  "price": 22.75
                },
                {
                  "name": "catteries",
                  "price": 22.1
                }
              ]
            }
          ]
        },
        {
          "name": "Cambridge",
          "petType": [
            {
              "name": "General",
              "careType": [
                {
                  "name": "pet sitting",
                  "price": 61.75
                }
              ]
            },
            {
              "name": "Dog",
              "careType": [
                {
                  "name": "dog sitting",
                  "price": 58.50
                },
                {
                  "name": "dog walking",
                  "price": 19.50
                },
                {
                  "name": "dog kennels",
                  "price": 31.85
                },
                {
                  "name": "doggy daycare",
                  "price": 49.40
                },
                {
                  "name": "dog drop-in visits",
                  "price": 15.60
                }
              ]
            },
            {
              "name": "Cat",
              "careType": [
                {
                  "name": "cat sitting",
                  "price": 58.50
                },
                {
                  "name": "cat drop-in visits",
                  "price": 26.00
                },
                {
                  "name": "catteries",
                  "price": 26.98
                }
              ]
            }
          ]
        },
        {
          "name": "Sheffield",
          "petType": [
            {
              "name": "General",
              "careType": [
                {
                  "name": "pet sitting",
                  "price": 71.5
                }
              ]
            },
            {
              "name": "Dog",
              "careType": [
                {
                  "name": "dog sitting",
                  "price": 78
                },
                {
                  "name": "dog walking",
                  "price": 22.75
                },
                {
                  "name": "dog kennels",
                  "price": 49.4
                },
                {
                  "name": "doggy daycare",
                  "price": 62.4
                },
                {
                  "name": "dog drop-in visits",
                  "price": 32.5
                }
              ]
            },
            {
              "name": "Cat",
              "careType": [
                {
                  "name": "cat sitting",
                  "price": 71.5
                },
                {
                  "name": "cat drop-in visits",
                  "price": 29.9
                },
                {
                  "name": "catteries",
                  "price": 27.3
                }
              ]
            }
          ]
        },
        {
          "name": "Leeds",
          "petType": [
            {
              "name": "General",
              "careType": [
                {
                  "name": "pet sitting",
                  "price": 78.00
                }
              ]
            },
            {
              "name": "Dog",
              "careType": [
                {
                  "name": "dog sitting",
                  "price": 78.00
                },
                {
                  "name": "dog walking",
                  "price": 13.00
                },
                {
                  "name": "dog kennels",
                  "price": 27.30
                },
                {
                  "name": "doggy daycare",
                  "price": 32.50
                },
                {
                  "name": "dog drop-in visits",
                  "price": 31.85
                }
              ]
            },
            {
              "name": "Cat",
              "careType": [
                {
                  "name": "cat sitting",
                  "price": 68.90
                },
                {
                  "name": "cat drop-in visits",
                  "price": 24.05
                },
                {
                  "name": "catteries",
                  "price": 14.30
                }
              ]
            }
          ]
        },
        {
          "name": "Bath",
          "petType": [
            {
              "name": "General",
              "careType": [
                {
                  "name": "pet sitting",
                  "price": 74.75
                }
              ]
            },
            {
              "name": "Dog",
              "careType": [
                {
                  "name": "dog sitting",
                  "price": 44.20
                },
                {
                  "name": "dog walking",
                  "price": 16.25
                },
                {
                  "name": "dog kennels",
                  "price": 40.95
                },
                {
                  "name": "doggy daycare",
                  "price": 40.30
                },
                {
                  "name": "dog drop-in visits",
                  "price": 19.50
                }
              ]
            },
            {
              "name": "Cat",
              "careType": [
                {
                  "name": "cat sitting",
                  "price": 74.75
                },
                {
                  "name": "cat drop-in visits",
                  "price": 19.50
                },
                {
                  "name": "catteries",
                  "price": 18.85
                }
              ]
            }
          ]
        },
        {
          "name": "Nottingham",
          "petType": [
            {
              "name": "General",
              "careType": [
                {
                  "name": "pet sitting",
                  "price": 71.50
                }
              ]
            },
            {
              "name": "Dog",
              "careType": [
                {
                  "name": "dog sitting",
                  "price": 71.50
                },
                {
                  "name": "dog walking",
                  "price": 16.25
                },
                {
                  "name": "dog kennels",
                  "price": 44.98
                },
                {
                  "name": "doggy daycare",
                  "price": 58.50
                },
                {
                  "name": "dog drop-in visits",
                  "price": 14.95
                }
              ]
            },
            {
              "name": "Cat",
              "careType": [
                {
                  "name": "cat sitting",
                  "price": 58.50
                },
                {
                  "name": "cat drop-in visits",
                  "price": 16.25
                },
                {
                  "name": "catteries",
                  "price": 13.00
                }
              ]
            }
          ]
        },
        {
          "name": "Birmingham",
          "petType": [
            {
              "name": "General",
              "careType": [
                {
                  "name": "pet sitting",
                  "price": 78.00
                }
              ]
            },
            {
              "name": "Dog",
              "careType": [
                {
                  "name": "dog sitting",
                  "price": 78.00
                },
                {
                  "name": "dog walking",
                  "price": 11.70
                },
                {
                  "name": "dog kennels",
                  "price": 39.00
                },
                {
                  "name": "doggy daycare",
                  "price": 32.50
                },
                {
                  "name": "dog drop-in visits",
                  "price": 22.10
                }
              ]
            },
            {
              "name": "Cat",
              "careType": [
                {
                  "name": "cat sitting",
                  "price": 78.00
                },
                {
                  "name": "cat drop-in visits",
                  "price": 16.25
                },
                {
                  "name": "catteries",
                  "price": 13.00
                }
              ]
            }
          ]
        },
        {
          "name": "Norwich",
          "petType": [
            {
              "name": "General",
              "careType": [
                {
                  "name": "pet sitting",
                  "price": 55.25
                }
              ]
            },
            {
              "name": "Dog",
              "careType": [
                {
                  "name": "dog sitting",
                  "price": 55.25
                },
                {
                  "name": "dog walking",
                  "price": 16.25
                },
                {
                  "name": "dog kennels",
                  "price": 35.10
                },
                {
                  "name": "doggy daycare",
                  "price": 28.60
                },
                {
                  "name": "dog drop-in visits",
                  "price": 19.50
                }
              ]
            },
            {
              "name": "Cat",
              "careType": [
                {
                  "name": "cat sitting",
                  "price": 58.50
                },
                {
                  "name": "cat drop-in visits",
                  "price": 15.60
                },
                {
                  "name": "catteries",
                  "price": 13.00
                }
              ]
            }
          ]
        },
        {
          "name": "Cardiff",
          "petType": [
            {
              "name": "General",
              "careType": [
                {
                  "name": "pet sitting",
                  "price": 65.00
                }
              ]
            },
            {
              "name": "Dog",
              "careType": [
                {
                  "name": "dog sitting",
                  "price": 78.00
                },
                {
                  "name": "dog walking",
                  "price": 18.20
                },
                {
                  "name": "dog kennels",
                  "price": 27.95
                },
                {
                  "name": "doggy daycare",
                  "price": 36.40
                },
                {
                  "name": "dog drop-in visits",
                  "price": 20.15
                }
              ]
            },
            {
              "name": "Cat",
              "careType": [
                {
                  "name": "cat sitting",
                  "price": 71.50
                },
                {
                  "name": "cat drop-in visits",
                  "price": 20.15
                },
                {
                  "name": "catteries",
                  "price": 12.03
                }
              ]
            }
          ]
        },
        {
          "name": "Bournemouth",
          "petType": [
            {
              "name": "General",
              "careType": [
                {
                  "name": "pet sitting",
                  "price": 56.55
                }
              ]
            },
            {
              "name": "Dog",
              "careType": [
                {
                  "name": "dog sitting",
                  "price": 56.55
                },
                {
                  "name": "dog walking",
                  "price": 16.25
                },
                {
                  "name": "dog kennels",
                  "price": 29.25
                },
                {
                  "name": "doggy daycare",
                  "price": 48.75
                },
                {
                  "name": "dog drop-in visits",
                  "price": 22.75
                }
              ]
            },
            {
              "name": "Cat",
              "careType": [
                {
                  "name": "cat sitting",
                  "price": 50.05
                },
                {
                  "name": "cat drop-in visits",
                  "price": 22.75
                },
                {
                  "name": "catteries",
                  "price": 23.40
                }
              ]
            }
          ]
        },
        {
          "name": "Liverpool",
          "petType": [
            {
              "name": "General",
              "careType": [
                {
                  "name": "pet sitting",
                  "price": 74.75
                }
              ]
            },
            {
              "name": "Dog",
              "careType": [
                {
                  "name": "dog sitting",
                  "price": 74.75
                },
                {
                  "name": "dog walking",
                  "price": 18.20
                },
                {
                  "name": "dog kennels",
                  "price": 28.60
                },
                {
                  "name": "doggy daycare",
                  "price": 35.10
                },
                {
                  "name": "dog drop-in visits",
                  "price": 12.35
                }
              ]
            },
            {
              "name": "Cat",
              "careType": [
                {
                  "name": "cat sitting",
                  "price": 58.50
                },
                {
                  "name": "cat drop-in visits",
                  "price": 16.25
                },
                {
                  "name": "catteries",
                  "price": 18.20
                }
              ]
            }
          ]
        },
        {
          "name": "Southampton",
          "petType": [
            {
              "name": "General",
              "careType": [
                {
                  "name": "pet sitting",
                  "price": 65.00
                }
              ]
            },
            {
              "name": "Dog",
              "careType": [
                {
                  "name": "dog sitting",
                  "price": 65.00
                },
                {
                  "name": "dog walking",
                  "price": 15.60
                },
                {
                  "name": "dog kennels",
                  "price": 27.95
                },
                {
                  "name": "doggy daycare",
                  "price": 22.10
                },
                {
                  "name": "dog drop-in visits",
                  "price": 18.85
                }
              ]
            },
            {
              "name": "Cat",
              "careType": [
                {
                  "name": "cat sitting",
                  "price": 65.00
                },
                {
                  "name": "cat drop-in visits",
                  "price": 18.85
                },
                {
                  "name": "catteries",
                  "price": 18.85
                }
              ]
            }
          ]
        },
        {
          "name": "York",
          "petType": [
            {
              "name": "General",
              "careType": [
                {
                  "name": "pet sitting",
                  "price": 48.75
                }
              ]
            },
            {
              "name": "Dog",
              "careType": [
                {
                  "name": "dog sitting",
                  "price": 48.75
                },
                {
                  "name": "dog walking",
                  "price": 13.00
                },
                {
                  "name": "dog kennels",
                  "price": 37.70
                },
                {
                  "name": "doggy daycare",
                  "price": 32.50
                },
                {
                  "name": "dog drop-in visits",
                  "price": 18.85
                }
              ]
            },
            {
              "name": "Cat",
              "careType": [
                {
                  "name": "cat sitting",
                  "price": 48.75
                },
                {
                  "name": "cat drop-in visits",
                  "price": 18.85
                },
                {
                  "name": "catteries",
                  "price": 18.20
                }
              ]
            }
          ]
        },
        {
          "name": "Belfast",
          "petType": [
            {
              "name": "General",
              "careType": [
                {
                  "name": "pet sitting",
                  "price": 68.25
                }
              ]
            },
            {
              "name": "Dog",
              "careType": [
                {
                  "name": "dog sitting",
                  "price": 68.25
                },
                {
                  "name": "dog walking",
                  "price": 15.60
                },
                {
                  "name": "dog kennels",
                  "price": 34.45
                },
                {
                  "name": "doggy daycare",
                  "price": 39.00
                },
                {
                  "name": "dog drop-in visits",
                  "price": 17.55
                }
              ]
            },
            {
              "name": "Cat",
              "careType": [
                {
                  "name": "cat sitting",
                  "price": 68.25
                },
                {
                  "name": "cat drop-in visits",
                  "price": 17.55
                },
                {
                  "name": "catteries",
                  "price": 18.85
                }
              ]
            }
          ]
        },
        {
          "name": "Newcastle",
          "petType": [
            {
              "name": "General",
              "careType": [
                {
                  "name": "pet sitting",
                  "price": 74.75
                }
              ]
            },
            {
              "name": "Dog",
              "careType": [
                {
                  "name": "dog sitting",
                  "price": 74.75
                },
                {
                  "name": "dog walking",
                  "price": 17.03
                },
                {
                  "name": "dog kennels",
                  "price": 25.35
                },
                {
                  "name": "doggy daycare",
                  "price": 29.90
                },
                {
                  "name": "dog drop-in visits",
                  "price": 24.70
                }
              ]
            },
            {
              "name": "Cat",
              "careType": [
                {
                  "name": "cat sitting",
                  "price": 74.75
                },
                {
                  "name": "cat drop-in visits",
                  "price": 15.60
                },
                {
                  "name": "catteries",
                  "price": 16.90
                }
              ]
            }
          ]
        }
      ]
    }
  ]
}